{
  "$schema": "https://static.modelcontextprotocol.io/schemas/2025-12-11/server.schema.json",
  "name": "io.github.vola-trebla/ndjson-local-log-triage-mcp",
  "description": "Streams NDJSON log triage: query patterns, detect anomalies, summarize timelines without full load.",
  "repository": {
    "url": "https://github.com/vola-trebla/ndjson-local-log-triage-mcp",
    "source": "github"
  },
  "version": "0.2.0",
  "packages": [
    {
      "registryType": "npm",
      "identifier": "ndjson-local-log-triage-mcp",
      "version": "0.2.0",
      "transport": {
        "type": "stdio"
      }
    }
  ]
}
